graphene_crud_maker/__init__.py
graphene_crud_maker/apps.py
graphene_crud_maker/core.py
graphene_crud_maker/utils.py
graphene_crud_maker/base/BaseMutation.txt
graphene_crud_maker/base/BaseQuery.txt
graphene_crud_maker/base/BaseRelay.txt
graphene_crud_maker/base/BaseSchema.txt
graphene_crud_maker/base/CoreSchema.txt
graphene_crud_maker/base/QueryBase.txt
graphene_crud_maker/base/__init__.py
graphene_crud_maker/management/commands/maker.py
graphene_crud_maker/migrations/__init__.py
graphene_crud_maker-1.2.0.dist-info/LICENSE
graphene_crud_maker-1.2.0.dist-info/METADATA
graphene_crud_maker-1.2.0.dist-info/WHEEL
graphene_crud_maker-1.2.0.dist-info/top_level.txt
graphene_crud_maker-1.2.0.dist-info/RECORD
